gras/__init__.py
gras/main.py
gras-0.0.3.dist-info/LICENSE
gras-0.0.3.dist-info/METADATA
gras-0.0.3.dist-info/WHEEL
gras-0.0.3.dist-info/entry_points.txt
gras-0.0.3.dist-info/RECORD
